crinkle/__init__.py
crinkle/context.py
crinkle/flow.py
crinkle/processor.py
crinkle-0.2.1.dist-info/LICENSE
crinkle-0.2.1.dist-info/METADATA
crinkle-0.2.1.dist-info/WHEEL
crinkle-0.2.1.dist-info/RECORD
